arianesaludo2/__init__.py
arianesaludo2/ariane.py
arianesaludo2-1.1.2.dist-info/METADATA
arianesaludo2-1.1.2.dist-info/WHEEL
arianesaludo2-1.1.2.dist-info/top_level.txt
arianesaludo2-1.1.2.dist-info/RECORD
