Metadata-Version: 2.1
Name: arianesaludo2
Version: 1.1.2
Summary: saludando2
Home-page: https://github.com/ivanriosrios/arianesaludo.git
Author: ivanrios
Author-email: ivanargemiroriosrios@gmail.com
License: UNKNOWN
Platform: UNKNOWN
Classifier: Development Status :: 3 - Alpha
Classifier: Intended Audience :: Developers
Classifier: Topic :: Software Development :: Libraries
Classifier: License :: OSI Approved :: MIT License
Classifier: Programming Language :: Python :: 3
Classifier: Programming Language :: Python :: 3.6
Classifier: Programming Language :: Python :: 3.7
Classifier: Programming Language :: Python :: 3.8
Classifier: Programming Language :: Python :: 3.9
